wttime/__init__.py
wttime/parser.py
wttime/strategy.py
wttime-0.1.data/scripts/wttime
wttime-0.1.dist-info/LICENSE.md
wttime-0.1.dist-info/METADATA
wttime-0.1.dist-info/WHEEL
wttime-0.1.dist-info/top_level.txt
wttime-0.1.dist-info/RECORD
